README
setup.py
smartflow/__init__.py
smartflow.egg-info/PKG-INFO
smartflow.egg-info/SOURCES.txt
smartflow.egg-info/dependency_links.txt
smartflow.egg-info/not-zip-safe
smartflow.egg-info/requires.txt
smartflow.egg-info/top_level.txt
smartflow/.sys/ATPG_SAF_template.ttf
smartflow/.sys/OSV_template.ttf
smartflow/.sys/atpg_saf.xls
smartflow/.sys/atpg_saf_fmax.xls
smartflow/.sys/atpg_saf_shmoo.xls
smartflow/.sys/atpg_saf_vmin.xls
smartflow/.sys/config_template.xls
smartflow/.sys/empty.ttf
smartflow/.sys/settings.csv
smartflow/flowchecker/TestFLowChecker.py
smartflow/flowchecker/__init__.py
smartflow/floweditor/TestFlowEditor.py
smartflow/floweditor/__init__.py
smartflow/flowgenerator/TestFlowGenerator.py
smartflow/flowgenerator/__init__.py
smartflow/flowparser/ConfigFile.py
smartflow/flowparser/TestFlow.py
smartflow/flowparser/TestFlowReader.py
smartflow/flowparser/TestFlowSection.py
smartflow/flowparser/TestFlowWriter.py
smartflow/flowparser/TestSuite.py
smartflow/flowparser/Testmethodparameter.py
smartflow/flowparser/Utils.py
smartflow/flowparser/__init__.py