Metadata-Version: 1.2
Name: smartflow
Version: 1.0.0
Summary: Library for generating and editing smartest7 test flow
Home-page: https://github.com/dylan516/smartflow.git
Author: Dylan
Author-email: dylan.adv@icloud.com
License: BSD
Keywords: testflow,smart
Platform: Any
Classifier: Development Status :: 5 - Production/Stable
Classifier: Intended Audience :: Developers
Classifier: License :: OSI Approved :: BSD License
Classifier: Programming Language :: Python
Classifier: Programming Language :: Python :: 2.7
Classifier: Programming Language :: Python :: 3
Classifier: Programming Language :: Python :: 3.4
Classifier: Programming Language :: Python :: 3.5
Classifier: Programming Language :: Python :: 3.6
Classifier: Operating System :: OS Independent
Classifier: Topic :: Software Development :: Libraries :: Python Modules
Requires-Python: >=2.7, !=3.0.*, !=3.1.*, !=3.2.*, !=3.3.*
